MANIFEST.in
README.md
setup.py
PyPrismatic.egg-info/PKG-INFO
PyPrismatic.egg-info/SOURCES.txt
PyPrismatic.egg-info/dependency_links.txt
PyPrismatic.egg-info/requires.txt
PyPrismatic.egg-info/top_level.txt
examples/Demo.ipynb
examples/debug_scompact.mrc
examples/debug_scompact_i.mrc
examples/debug_scompact_r.mrc
examples/qxaReduce.mrc
examples/qxaShift.mrc
examples/thickness_scan.py
examples/thickness_scan.sh
examples/thickness_scan1.mrc
examples/thickness_scan10.mrc
examples/thickness_scan11.mrc
examples/thickness_scan12.mrc
examples/thickness_scan13.mrc
examples/thickness_scan14.mrc
examples/thickness_scan15.mrc
examples/thickness_scan16.mrc
examples/thickness_scan2.mrc
examples/thickness_scan3.mrc
examples/thickness_scan4.mrc
examples/thickness_scan5.mrc
examples/thickness_scan6.mrc
examples/thickness_scan7.mrc
examples/thickness_scan8.mrc
examples/thickness_scan9.mrc
examples/untitled
include/ArrayND.h
include/Multislice_calcOutput.cuh
include/Multislice_calcOutput.h
include/Multislice_entry.h
include/PRISM01_calcPotential.h
include/PRISM02_calcSMatrix.cuh
include/PRISM02_calcSMatrix.h
include/PRISM03_calcOutput.cuh
include/PRISM03_calcOutput.h
include/PRISM_entry.h
include/WorkDispatcher.h
include/atom.h
include/configure.h
include/cuprismatic.h
include/defines.h
include/go.h
include/kirkland_params.h
include/meta.h
include/params.cuh
include/params.h
include/parseInput.h
include/prism_qthreads.h
include/projectedPotential.h
include/utility.cuh
include/utility.h
pyprismatic/__init__.py
pyprismatic/core.cpp
pyprismatic/fileio.py
pyprismatic/params.py
src/Multislice_calcOutput.cpp
src/Multislice_entry.cpp
src/PRISM01_calcPotential.cpp
src/PRISM02_calcSMatrix.cpp
src/PRISM03_calcOutput.cpp
src/PRISM_entry.cpp
src/WorkDispatcher.cpp
src/atom.cpp
src/configure.cpp
src/driver.cpp
src/go.cpp
src/parseInput.cpp
src/projectedPotential.cpp
src/utility.cpp