Metadata-Version: 1.0
Name: PyPrismatic
Version: 1.1.16
Summary: Python wrapper for Prismatic package for fast image simulation using the PRISM and multislice algorithms in Scanning Transmission Electron Microscopy (STEM)
Home-page: UNKNOWN
Author: Alan (AJ) Pryor, Jr.
Author-email: apryor6@gmail.com
License: UNKNOWN
Platform: UNKNOWN
